MANIFEST.in
README.md
README.rst
setup.cfg
setup.py
yasi.py
tests/cases/#1-if-expression.lisp
tests/cases/#1-if-expression~.lisp
tests/cases/#15-input-space-output-tabs.lisp
tests/cases/#15-input-space-output-tabs~.lisp
tests/cases/#16-lisp-flets-and-labels.lisp
tests/cases/#16-lisp-flets-and-labels~.lisp
tests/cases/#19-hash-quoted-expressions.lisp
tests/cases/#19-hash-quoted-expressions~.lisp
tests/cases/#2-multiple-value-bind.lisp
tests/cases/#2-multiple-value-bind~.lisp
tests/cases/#20-unclosed-string.lisp
tests/cases/#20-unclosed-string~.lisp
tests/cases/#21-closing-brackets-separate-lines.lisp
tests/cases/#21-closing-brackets-separate-lines~.lisp
tests/cases/#22-defmacro-example.lisp
tests/cases/#22-defmacro-example~.lisp
tests/cases/#3-multiple-value-bind.lisp
tests/cases/#3-multiple-value-bind~.lisp
tests/cases/#4-flet-indentation.lisp
tests/cases/#4-flet-indentation~.lisp
tests/cases/#5-looks-like-a-macro.lisp
tests/cases/#5-looks-like-a-macro~.lisp
tests/cases/#6-default-indent.lisp
tests/cases/#6-default-indent~.lisp
tests/cases/#7-uniform-if-expression.lisp
tests/cases/#7-uniform-if-expression~.lisp
tests/cases/#8-macrolet-special-operator.lisp
tests/cases/#8-macrolet-special-operator~.lisp
tests/cases/#9-standard-emacs-form-indentation.lisp
tests/cases/#9-standard-emacs-form-indentation~.lisp
yasi.egg-info/PKG-INFO
yasi.egg-info/SOURCES.txt
yasi.egg-info/dependency_links.txt
yasi.egg-info/entry_points.txt
yasi.egg-info/requires.txt
yasi.egg-info/top_level.txt