Metadata-Version: 2.1
Name: yasi
Version: 2.1.2
Summary: A dialect aware s-expression indenter
Home-page: https://github.com/nkmathew/yasi-sexp-indenter
Author: Mathew Ng'etich
Author-email: kipkoechmathew@gmail.com
License: UNKNOWN
Download-URL: https://github.com/nkmathew/yasi-sexp-indenter/zipball/master
Keywords: scheme,formatter,newlisp,beautifier,clojure,lisp,indenter
Platform: UNKNOWN
Classifier: Development Status :: 5 - Production/Stable
Classifier: Environment :: Console
Classifier: Intended Audience :: Developers
Classifier: License :: OSI Approved
Classifier: License :: OSI Approved :: MIT License
Classifier: Natural Language :: English
Classifier: Operating System :: OS Independent
Classifier: Programming Language :: Python
Classifier: Programming Language :: Python :: 2
Classifier: Programming Language :: Python :: 2.7
Classifier: Programming Language :: Python :: 3
Classifier: Programming Language :: Python :: 3.4
Classifier: Programming Language :: Python :: 3.5
Classifier: Programming Language :: Python :: 3.6
Classifier: Programming Language :: Python :: 3.7
Classifier: Programming Language :: Python :: 3.8
Classifier: Topic :: Software Development :: Quality Assurance
